[	
        {"drawDate": "04-01-2023", "one" : "18*16", "two" : "11*05", "three" : "36*02"},
        {"drawDate": "04-02-2023", "one" : "15*08", "two" : "19*11", "three" : "14*06"},
	{"drawDate": "04-03-2023", "one" : "33*13", "two" : "12*23", "three" : "23*24"},
	{"drawDate": "04-04-2023", "one" : "20*18", "two" : "03*28", "three" : "29*16"},
	{"drawDate": "04-05-2023", "one" : "18*04", "two" : "04*30", "three" : "15*08"},
	{"drawDate": "04-10-2023", "one" : "11*20", "two" : "", "three" : ""}
]
